{
	"info": {
		"_postman_id": "946c4c8e-c083-4357-91dd-6b1a07cde274",
		"name": "K8S",
		"schema": "https://schema.getpostman.com/json/collection/v2.1.0/collection.json"
	},
	"item": [
		{
			"name": "Platform Service",
			"item": [
				{
					"name": "Get All Platforms Copy",
					"request": {
						"method": "GET",
						"header": [],
						"url": {
							"raw": "http://localhost:8080/api/platforms",
							"protocol": "http",
							"host": [
								"localhost"
							],
							"port": "8080",
							"path": [
								"api",
								"platforms"
							]
						}
					},
					"response": []
				}
			]
		}
	]
}